AUTHORS.rst
CONTRIBUTING.rst
HISTORY.rst
LICENSE
MANIFEST.in
README.rst
setup.cfg
setup.py
docs/Makefile
docs/authors.rst
docs/conf.py
docs/contributing.rst
docs/history.rst
docs/index.rst
docs/installation.rst
docs/make.bat
docs/modules.rst
docs/readme.rst
docs/usage.rst
docs/wordstart.rst
docs/_build/html/_static/ajax-loader.gif
docs/_build/html/_static/comment-bright.png
docs/_build/html/_static/comment-close.png
docs/_build/html/_static/comment.png
docs/_build/html/_static/down-pressed.png
docs/_build/html/_static/down.png
docs/_build/html/_static/file.png
docs/_build/html/_static/minus.png
docs/_build/html/_static/plus.png
docs/_build/html/_static/up-pressed.png
docs/_build/html/_static/up.png
tests/test_wordstart.py
wordstart/__init__.py
wordstart/cli.py
wordstart/wordstart.py
wordstart.egg-info/PKG-INFO
wordstart.egg-info/SOURCES.txt
wordstart.egg-info/dependency_links.txt
wordstart.egg-info/entry_points.txt
wordstart.egg-info/not-zip-safe
wordstart.egg-info/requires.txt
wordstart.egg-info/top_level.txt