Metadata-Version: 1.1
Name: wordstart
Version: 0.1.0
Summary: Prints the words in the given string that start with the given letter
Home-page: https://github.com/mmlmpa/wordstart
Author: Monica Londono
Author-email: monilondo@gmail.com
License: MIT license
Keywords: wordstart
Platform: UNKNOWN
Classifier: Development Status :: 2 - Pre-Alpha
Classifier: Intended Audience :: Developers
Classifier: License :: OSI Approved :: MIT License
Classifier: Natural Language :: English
Classifier: Programming Language :: Python :: 2
Classifier: Programming Language :: Python :: 2.7
Classifier: Programming Language :: Python :: 3
Classifier: Programming Language :: Python :: 3.4
Classifier: Programming Language :: Python :: 3.5
Classifier: Programming Language :: Python :: 3.6
